[
{"A2M ": ["A2MD", " CPAMD5", " FWP007", " S863-7", "A2M "]},
{"A2ML1 ": ["CPAMD9", " OMS", " p170", "A2ML1 "]},
{"A4GALT ": ["A14GALT", " A4GALT1", " Gb3S", " P(k)", " P1", " P1PK", " PK", "A4GALT "]},
{"AAAS ": ["AAA", " AAASb", " ADRACALA", " ADRACALIN", " ALADIN", " GL003", "AAAS "]},
{"AAGAB ": ["KPPP1", " PPKP1", " PPKP1A", " p34", "AAGAB "]},
{"AARS1 ": ["AARS", " CMT2N", " EIEE29", "AARS1 "]},
{"AARS2 ": ["AARSL", " COXPD8", " LKENP", " MT-ALARS", " MTALARS", "AARS2 "]},
{"AASS ": ["LKR/SDH", " LKRSDH", " LORSDH", "AASS "]},
{"ABAT ": ["GABA-AT", " GABAT", " NPD009", "ABAT "]},
{"ABCA1 ": ["ABC-1", " ABC1", " CERP", " HDLCQTL13", " HDLDT1", " HPALP1", " TGD", "ABCA1 "]},
{"ABCA12 ": ["ARCI4A", " ARCI4B", " ICR2B", " LI2", "ABCA12 "]},
{"ABCA2 ": ["ABC2", " IDPOGSA", "ABCA2 "]},
{"ABCA3 ": ["ABC-C", " ABC3", " EST111653", " LBM180", " SMDP3", "ABCA3 "]},
{"ABCA4 ": ["ABC10", " ABCR", " ARMD2", " CORD3", " FFM", " RMP", " RP19", " STGD", " STGD1", "ABCA4 "]},
{"ABCA5 ": ["ABC13", " EST90625", " HTC3", "ABCA5 "]},
{"ABCA7 ": ["ABCA-SSN", " ABCX", " AD9", "ABCA7 "]},
{"ABCB1 ": ["ABC20", " CD243", " CLCS", " GP170", " MDR1", " P-GP", " PGY1", "ABCB1 "]},
{"ABCB11 ": ["ABC16", " BRIC2", " BSEP", " PFIC-2", " PFIC2", " PGY4", " SPGP", "ABCB11 "]},
{"ABCB4 ": ["ABC21", " GBD1", " ICP3", " MDR2", " MDR2/3", " MDR3", " PFIC-3", " PGY3", "ABCB4 "]},
{"ABCB6 ": ["ABC", " LAN", " MTABC3", " PRP", " umat", "ABCB6 "]},
{"ABCB7 ": ["ABC7", " ASAT", " Atm1p", " EST140535", "ABCB7 "]},
{"ABCC11 ": ["EWWD", " MRP8", " WW", "ABCC11 "]},
{"ABCC2 ": ["ABC30", " CMOAT", " DJS", " MRP2", " cMRP", "ABCC2 "]},
{"ABCC6 ": ["ABC34", " ARA", " EST349056", " GACI2", " MLP1", " MOAT-E", " MOATE", " MRP6", " PXE", " PXE1", " URG7", "ABCC6 "]},
{"ABCC8 ": ["ABC36", " HHF1", " HI", " HRINS", " MRP8", " PHHI", " PNDM3", " SUR", " SUR1", " SUR1delta2", " TNDM2", "ABCC8 "]},
{"ABCC9 ": ["ABC37", " ATFB12", " CANTU", " CMD1O", " SUR2", "ABCC9 "]},
{"ABCD1 ": ["ABC42", " ALD", " ALDP", " AMN", "ABCD1 "]},
{"ABCD3 ": ["ABC43", " CBAS5", " PMP70", " PXMP1", " ZWS2", "ABCD3 "]},
{"ABCD4 ": ["ABC41", " EST352188", " MAHCJ", " P70R", " P79R", " PMP69", " PXMP1L", "ABCD4 "]},
{"ABCG2 ": ["ABC15", " ABCP", " BCRP", " BCRP1", " BMDP", " CD338", " CDw338", " EST157481", " GOUT1", " MRX", " MXR", " MXR-1", " MXR1", " UAQTL1", "ABCG2 "]},
{"ABCG5 ": ["STSL", " STSL2", "ABCG5 "]},
{"ABCG8 ": ["GBD4", " STSL", " STSL1", "ABCG8 "]},
{"ABHD12 ": ["ABHD12A", " BEM46L2", " C20orf22", " PHARC", " dJ965G21.2", " hABHD12", "ABHD12 "]},
{"ABHD5 ": ["CGI58", " IECN2", " NCIE2", "ABHD5 "]},
{"ABL1 ": ["ABL", " BCR-ABL", " CHDSKM", " JTK7", " bcr/abl", " c-ABL", " c-ABL1", " p150", " v-abl", "ABL1 "]},
{"ABO ": ["A3GALNT", " A3GALT1", " GTB", " NAGAT", "ABO "]},
{"ACACA ": ["ACAC", " ACACAD", " ACC", " ACC1", " ACCA", "ACACA "]},
{"ACAD8 ": ["ACAD-8", " ARC42", " IBDH", "ACAD8 "]},
{"ACAD9 ": ["MC1DN20", " NPD002", "ACAD9 "]},
{"ACADM ": ["ACAD1", " MCAD", " MCADH", "ACADM "]},
{"ACADS ": ["ACAD3", " SCAD", "ACADS "]},
{"ACADSB ": ["2-MEBCAD", " ACAD7", " SBCAD", "ACADSB "]},
{"ACADVL ": ["ACAD6", " LCACD", " VLCAD", "ACADVL "]},
{"ACAN ": ["AGC1", " AGCAN", " CSPG1", " CSPGCP", " MSK16", " SEDK", " SSOAOD", "ACAN "]},
{"ACAT1 ": ["ACAT", " MAT", " T2", " THIL", "ACAT1 "]},
{"ACAT2 ": ["ACAT2 "]},
{"ACD ": ["PIP1", " PTOP", " TINT1", " TPP1", "ACD "]},
{"ACE ": ["ACE1", " CD143", " DCP", " DCP1", "ACE "]},
{"ACER3 ": ["APHC", " PHCA", " PLDECO", "ACER3 "]},
{"ACHE ": ["ACEE", " ARACHE", " N-ACHE", " YT", "ACHE "]},
{"ACKR1 ": ["CCBP1", " CD234", " DARC", " DARC/ACKR1", " Dfy", " FY", " GPD", " GpFy", " WBCQ1", "ACKR1 "]},
{"ACO2 ": ["ACONM", " HEL-S-284", " ICRD", " OCA8", " OPA9", "ACO2 "]},
{"ACOX1 ": ["ACOX", " PALMCOX", " SCOX", "ACOX1 "]},
{"ACOX2 ": ["BCOX", " BRCACOX", " BRCOX", " CBAS6", " THCCox", "ACOX2 "]},
{"ACP2 ": ["LAP", "ACP2 "]},
{"ACP4 ": ["ACPT", " AI1J", "ACP4 "]},
{"ACP5 ": ["HPAP", " TRACP5a", " TRACP5b", " TRAP", " TrATPase", "ACP5 "]},
{"ACSF3 ": ["ACSF3 "]},
{"ACSL4 ": ["ACS4", " FACL4", " LACS4", " MRX63", " MRX68", "ACSL4 "]},
{"ACTA1 ": ["ACTA", " ASMA", " CFTD", " CFTD1", " CFTDM", " MPFD", " NEM1", " NEM2", " NEM3", " SHPM", "ACTA1 "]},
{"ACTA2 ": ["ACTSA", "ACTA2 "]},
{"ACTB ": ["BRWS1", " PS1TP5BP1", "ACTB "]},
{"ACTC1 ": ["ACTC", " ASD5", " CMD1R", " CMH11", " LVNC4", "ACTC1 "]},
{"ACTG1 ": ["ACT", " ACTG", " DFNA20", " DFNA26", " HEL-176", "ACTG1 "]},
{"ACTG2 ": ["ACT", " ACTA3", " ACTE", " ACTL3", " ACTSG", " VSCM", "ACTG2 "]},
{"ACTL6B ": ["ACTL6", " BAF53B", " EIEE76", " IDDSSAD", " arpNalpha", "ACTL6B "]},
{"ACTN1 ": ["BDPLT15", "ACTN1 "]},
{"ACTN2 ": ["CMD1AA", " CMH23", " MPD6", " MYOCOZ", "ACTN2 "]},
{"ACTN3 ": ["ACTN3D", "ACTN3 "]},
{"ACTN4 ": ["ACTININ-4", " FSGS", " FSGS1", "ACTN4 "]},
{"ACVR1 ": ["ACTRI", " ACVR1A", " ACVRLK2", " ALK2", " FOP", " SKR1", " TSRI", "ACVR1 "]},
{"ACVR2B ": ["ACTRIIB", " ActR-IIB", " HTX4", "ACVR2B "]},
{"ACVRL1 ": ["ACVRLK1", " ALK-1", " ALK1", " HHT", " HHT2", " ORW2", " SKR3", " TSR-I", "ACVRL1 "]},
{"ACY1 ": ["ACY-1", " ACY1D", " HEL-S-5", "ACY1 "]},
{"ADA ": ["ADA "]},
{"ADA2 ": ["ADGF", " CECR1", " IDGFL", " PAN", " SNEDS", " VAIHS", "ADA2 "]},
{"ADAM10 ": ["AD10", " AD18", " CD156c", " CDw156", " HsT18717", " MADM", " RAK", " kuz", "ADAM10 "]},
{"ADAM17 ": ["ADAM18", " CD156B", " CSVP", " NISBD", " NISBD1", " TACE", "ADAM17 "]},
{"ADAM22 ": ["ADAM 22", " EIEE61", " MDC2", "ADAM22 "]},
{"ADAM9 ": ["CORD9", " MCMP", " MDC9", " Mltng", "ADAM9 "]},
{"ADAMTS10 ": ["ADAM-TS10", " ADAMTS-10", " WMS", " WMS1", "ADAMTS10 "]},
{"ADAMTS13 ": ["ADAM-TS13", " ADAMTS-13", " C9orf8", " VWFCP", " vWF-CP", "ADAMTS13 "]},
{"ADAMTS17 ": ["WMS4", "ADAMTS17 "]},
{"ADAMTS18 ": ["ADAMTS21", " KNO2", " MMCAT", "ADAMTS18 "]},
{"ADAMTS2 ": ["ADAM-TS2", " ADAMTS-2", " ADAMTS-3", " EDSDERMS", " NPI", " PC I-NP", " PCI-NP", " PCINP", " PCPNI", " PNPI", "ADAMTS2 "]},
{"ADAMTS3 ": ["ADAMTS-4", " HKLLS3", "ADAMTS3 "]},
{"ADAMTSL2 ": ["ADAMTSL-2", " GPHYSD1", "ADAMTSL2 "]},
{"ADAMTSL4 ": ["ADAMTSL-4", " ECTOL2", " TSRC1", "ADAMTSL4 "]},
{"ADAR ": ["ADAR1", " AGS6", " DRADA", " DSH", " DSRAD", " G1P1", " IFI-4", " IFI4", " K88DSRBP", " P136", "ADAR "]},
{"ADAT3 ": ["FWP005", " MRT36", " MST121", " MSTP121", " S863-5", " TAD3", "ADAT3 "]},
{"ADCY1 ": ["AC1", " DFNB44", "ADCY1 "]},
{"ADCY10 ": ["HCA2", " HEL-S-7a", " SAC", " SACI", " Sacy", " hsAC", "ADCY10 "]},
{"ADCY3 ": ["AC-III", " AC3", " BMIQ19", "ADCY3 "]},
{"ADCY5 ": ["AC5", " FDFM", "ADCY5 "]},
{"ADCY6 ": ["AC6", " LCCS8", "ADCY6 "]},
{"ADD1 ": ["ADDA", "ADD1 "]},
{"ADD3 ": ["ADDL", " CPSQ3", "ADD3 "]},
{"ADGRE2 ": ["CD312", " CD97", " EMR2", " VBU", "ADGRE2 "]},
{"ADGRG1 ": ["BFPP", " BPPR", " GPR56", " TM7LN4", " TM7XN1", "ADGRG1 "]},
{"ADGRG2 ": ["CBAVDX", " EDDM6", " GPR64", " HE6", " TM7LN2", "ADGRG2 "]},
{"ACKR1 ": ["CCBP1", " CD234", " DARC", " DARC/ACKR1", " Dfy", " FY", " GPD", " GpFy", " WBCQ1", "ACKR1 "]},
{"ADGRV1 ": ["FEB4", " GPR98", " MASS1", " USH2B", " USH2C", " VLGR1", " VLGR1b", "ADGRV1 "]},
{"ADH1B ": ["ADH2", " HEL-S-117", "ADH1B "]},
{"ADH1C ": ["ADH3", "ADH1C "]},
{"ADIPOQ ": ["ACDC", " ACRP30", " ADIPQTL1", " ADPN", " APM-1", " APM1", " GBP28", "ADIPOQ "]},
{"ADK ": ["AK", "ADK "]},
{"ADNP ": ["ADNP1", " HVDAS", " MRD28", "ADNP "]},
{"ADPRS ": ["ADPRHL2", " ARH3", " CONDSIAS", "ADPRS "]},
{"ADRB1 ": ["ADRB1R", " B1AR", " BETA1AR", " FNSS2", " RHR", "ADRB1 "]},
{"ADRB2 ": ["ADRB2R", " ADRBR", " B2AR", " BAR", " BETA2AR", "ADRB2 "]},
{"ADRB3 ": ["BETA3AR", "ADRB3 "]},
{"ADSL ": ["AMPS", " ASASE", " ASL", "ADSL "]},
{"ADSS1 ": ["ADSSL1", " MPD5", "ADSS1 "]},
{"AEBP1 ": ["ACLP", "AEBP1 "]},
{"AFF2 ": ["FMR2", " FMR2P", " FRAXE", " MRX2", " OX19", "AFF2 "]},
{"AFF4 ": ["AF5Q31", " CHOPS", " MCEF", "AFF4 "]},
{"AFG3L2 ": ["SCA28", " SPAX5", "AFG3L2 "]},
{"AFP ": ["AFPD", " FETA", " HPAFP", "AFP "]},
{"AGA ": ["AGU", " ASRG", " GA", "AGA "]},
{"AGBL1 ": ["CCP4", " FECD8", "AGBL1 "]},
{"AGBL5 ": ["CCP5", " RP75", "AGBL5 "]},
{"AGK ": ["CATC5", " CTRCT38", " MTDPS10", " MULK", "AGK "]},
{"AGL ": ["GDE", "AGL "]},
{"AGPAT2 ": ["1-AGPAT2", " BSCL", " BSCL1", " LPAAB", " LPAAT-beta", "AGPAT2 "]},
{"AGPS ": ["ADAP-S", " ADAS", " ADHAPS", " ADPS", " ALDHPSY", " RCDP3", "AGPS "]},
{"AGRN ": ["AGRIN", " CMS8", " CMSPPD", "AGRN "]},
{"AGRP ": ["AGRT", " ART", " ASIP2", "AGRP "]},
{"AGT ": ["ANHU", " SERPINA8", " hFLT1", "AGT "]},
{"AGTPBP1 ": ["CCP1", " CONDCA", " NNA1", "AGTPBP1 "]},
{"AGTR1 ": ["AG2S", " AGTR1B", " AT1", " AT1AR", " AT1B", " AT1BR", " AT1R", " AT2R1", " HAT1R", "AGTR1 "]},
{"AGXT ": ["AGT", " AGT1", " AGXT1", " PH1", " SPAT", " SPT", " TLH6", "AGXT "]},
{"AGXT2 ": ["AGT2", " BAIBA", " DAIBAT", "AGXT2 "]},
{"AHCY ": ["SAHH", " adoHcyase", "AHCY "]},
{"AHDC1 ": ["MRD25", " XIGIS", "AHDC1 "]},
{"AHI1 ": ["AHI-1", " JBTS3", " ORF1", " dJ71N10.1", "AHI1 "]},
{"AHR ": ["RP85", " bHLHe76", "AHR "]},
{"AHSG ": ["A2HS", " AHS", " APMR1", " FETUA", " HSGA", "AHSG "]},
{"AICDA ": ["AID", " ARP2", " CDA2", " HEL-S-284", " HIGM2", "AICDA "]},
{"AIFM1 ": ["AIF", " AUNX1", " CMT2D", " CMTX4", " COWCK", " COXPD6", " DFNX5", " NADMR", " NAMSD", " PDCD8", " SEMDHL", "AIFM1 "]},
{"AIMP1 ": ["EMAP2", " EMAPII", " HLD3", " SCYE1", " p43", "AIMP1 "]},
{"AIMP2 ": ["HLD17", " JTV-1", " JTV1", " P38", "AIMP2 "]},
{"AIP ": ["ARA9", " FKBP16", " FKBP37", " PITA1", " SMTPHN", " XAP-2", " XAP2", "AIP "]},
{"AIPL1 ": ["AIPL2", " LCA4", "AIPL1 "]},
{"AIRE ": ["AIRE1", " APECED", " APS1", " APSI", " PGA1", "AIRE "]},
{"AK1 ": ["HTL-S-58j", "AK1 "]},
{"AK2 ": ["ADK2", "AK2 "]},
{"AK7 ": ["AK 7", " CFAP75", " FAP75", " SPGF27", "AK7 "]},
{"AKAP10 ": ["AKAP-10", " D-AKAP-2", " D-AKAP2", " PRKA10", "AKAP10 "]},
{"AKAP9 ": ["AKAP-9", " AKAP350", " AKAP450", " CG-NAP", " HYPERION", " LQT11", " MU-RMS-40.16A", " PPP1R45", " PRKA9", " YOTIAO", "AKAP9 "]},
{"AKR1C2 ": ["AKR1C-pseudo", " BABP", " DD", " DD-2", " DD/BABP", " DD2", " DDH2", " HAKRD", " HBAB", " MCDR2", " SRXY8", " TDD", "AKR1C2 "]},
{"ACKR1 ": ["CCBP1", " CD234", " DARC", " DARC/ACKR1", " Dfy", " FY", " GPD", " GpFy", " WBCQ1", "ACKR1 "]},
{"AKR1D1 ": ["3o5bred", " CBAS2", " SRD5B1", "AKR1D1 "]},
{"AKT1 ": ["AKT", " CWS6", " PKB", " PKB-ALPHA", " PRKBA", " RAC", " RAC-ALPHA", "AKT1 "]},
{"AKT2 ": ["HIHGHH", " PKBB", " PKBBETA", " PRKBB", " RAC-BETA", "AKT2 "]},
{"AKT3 ": ["MPPH", " MPPH2", " PKB-GAMMA", " PKBG", " PRKBG", " RAC-PK-gamma", " RAC-gamma", " STK-2", "AKT3 "]},
{"ALAD ": ["ALADH", " PBGS", "ALAD "]},
{"ALAS2 ": ["ALAS-E", " ALASE", " ANH1", " ASB", " SIDBA1", " XLDPP", " XLEPP", " XLSA", "ALAS2 "]},
{"ALB ": ["HSA", " PRO0883", " PRO0903", " PRO1341", "ALB "]},
{"ALDH18A1 ": ["ADCL3", " ARCL3A", " GSAS", " P5CS", " PYCS", " SPG9", " SPG9A", " SPG9B", "ALDH18A1 "]},
{"ALDH1A3 ": ["ALDH1A6", " ALDH6", " MCOP8", " RALDH3", "ALDH1A3 "]},
{"ALDH2 ": ["ALDH-E2", " ALDHI", " ALDM", "ALDH2 "]},
{"ALDH3A2 ": ["ALDH10", " FALDH", " SLS", "ALDH3A2 "]},
{"ALDH4A1 ": ["ALDH4", " P5CD", " P5CDh", "ALDH4A1 "]},
{"ALDH5A1 ": ["SSADH", " SSDH", "ALDH5A1 "]},
{"ALDH6A1 ": ["MMSADHA", " MMSDH", "ALDH6A1 "]},
{"ALDH7A1 ": ["ATQ1", " EPD", " PDE", "ALDH7A1 "]},
{"ALDOA ": ["ALDA", " GSD12", " HEL-S-87p", "ALDOA "]},
{"ALDOB ": ["ALDB", " ALDO2", "ALDOB "]},
{"ALG1 ": ["CDG1K", " HMAT1", " HMT-1", " HMT1", " MT-1", " Mat-1", " hMat-1", "ALG1 "]},
{"ALG10B ": ["ALG10", " KCR1", "ALG10B "]},
{"ALG11 ": ["CDG1P", " GT8", "ALG11 "]},
{"ALG12 ": ["CDG1G", " ECM39", " PP14673", " hALG12", "ALG12 "]},
{"ALG13 ": ["CDG1S", " CXorf45", " EIEE36", " GLT28D1", " MDS031", " TDRD13", " YGL047W", "ALG13 "]},
{"ALG14 ": ["CMS15", "ALG14 "]},
{"ALG2 ": ["CDG1I", " CDGIi", " CMS14", " CMSTA3", " NET38", " hALPG2", "ALG2 "]},
{"ALG3 ": ["CDG1D", " CDGS4", " CDGS6", " D16Ertd36e", " NOT56L", " Not56", " not", "ALG3 "]},
{"ALG6 ": ["CDG1C", "ALG6 "]},
{"ALG8 ": ["CDG1H", " PCLD3", "ALG8 "]},
{"ALG9 ": ["CDG1L", " DIBD1", " GIKANIS", " LOH11CR1J", "ALG9 "]},
{"ALK ": ["CD246", " NBLST3", "ALK "]},
{"ALKBH8 ": ["ABH8", " MRT71", " TRM9", " TRMT9", " TRMT9A", "ALKBH8 "]},
{"ALMS1 ": ["ALSS", "ALMS1 "]},
{"ALOX12B ": ["12R-LOX", " ARCI2", "ALOX12B "]},
{"ALOX5 ": ["5-LO", " 5-LOX", " 5LPG", " LOG5", "ALOX5 "]},
{"ALOX5AP ": ["FLAP", "ALOX5AP "]},
{"ALOXE3 ": ["ARCI3", " E-LOX", " eLOX-3", " eLOX3", "ALOXE3 "]},
{"ALPK3 ": ["CMH27", " MAK", " MIDORI", "ALPK3 "]},
{"ALPL ": ["AP-TNAP", " APTNAP", " HOPS", " TNALP", " TNAP", " TNSALP", "ALPL "]},
{"ALS2 ": ["ALS2CR6", " ALSJ", " IAHSP", " PLSJ", "ALS2 "]},
{"ALX1 ": ["CART1", " FND3", " HEL23", "ALX1 "]},
{"ALX3 ": ["FND", " FND1", "ALX3 "]},
{"ALX4 ": ["CRS5", " FND2", "ALX4 "]},
{"AMACR ": ["AMACRD", " CBAS4", " P504S", " RACE", " RM", "AMACR "]},
{"AMBN ": ["AI1F", "AMBN "]},
{"AMELX ": ["AI1E", " AIH1", " ALGN", " AMG", " AMGL", " AMGX", "AMELX "]},
{"AMER1 ": ["FAM123B", " OSCS", " WTX", "AMER1 "]},
{"AMH ": ["MIF", " MIS", "AMH "]},
{"AMHR2 ": ["AMHR", " MISR2", " MISRII", " MRII", "AMHR2 "]},
{"AMMECR1 ": ["AMMERC1", " MFHIEN", "AMMECR1 "]},
{"AMN ": ["IGS2", " PRO1028", " amnionless", "AMN "]},
{"ACKR1 ": ["CCBP1", " CD234", " DARC", " DARC/ACKR1", " Dfy", " FY", " GPD", " GpFy", " WBCQ1", "ACKR1 "]},
{"AMPD2 ": ["PCH9", " SPG63", "AMPD2 "]},
{"AMPD3 ": ["AMPD3 "]},
{"AMT ": ["GCE", " GCST", " GCVT", " NKH", "AMT "]},
{"AMTN ": ["AI3B", " UNQ689", "AMTN "]},
{"ANAPC1 ": ["APC1", " MCPR", " TSG24", "ANAPC1 "]},
{"ANG ": ["ALS9", " HEL168", " RAA1", " RNASE4", " RNASE5", "ANG "]},
{"ANGPTL3 ": ["ANG-5", " ANGPT5", " ANL3", " FHBL2", "ANGPTL3 "]},
{"ANGPTL4 ": ["ARP4", " FIAF", " HARP", " HFARP", " NL2", " PGAR", " TGQTL", " UNQ171", " pp1158", "ANGPTL4 "]},
{"ANK1 ": ["ANK", " SPH1", " SPH2", "ANK1 "]},
{"ANK2 ": ["ANK-2", " CFAP87", " FAP87", " LQT4", " brank-2", "ANK2 "]},
{"ANK3 ": ["ANKYRIN-G", " MRT37", "ANK3 "]},
{"ANKH ": ["ANK", " CCAL2", " CMDJ", " CPPDD", " HANK", " MANK", " SLC62A1", "ANKH "]},
{"ANKLE2 ": ["KIAA0692", " LEMD7", " Lem4", " MCPH16", "ANKLE2 "]},
{"ANKRD11 ": ["ANCO-1", " ANCO1", " LZ16", " T13", "ANKRD11 "]},
{"ANKRD26 ": ["THC2", " bA145E8.1", "ANKRD26 "]},
{"ANKS6 ": ["ANKRD14", " NPHP16", " PKDR1", " SAMD6", "ANKS6 "]},
{"ANLN ": ["FSGS8", " Scraps", " scra", "ANLN "]},
{"ANO10 ": ["SCAR10", " TMEM16K", "ANO10 "]},
{"ANO3 ": ["C11orf25", " DYT23", " DYT24", " GENX-3947", " TMEM16C", "ANO3 "]},
{"ANO5 ": ["GDD1", " LGMD2L", " LGMDR12", " TMEM16E", "ANO5 "]},
{"ANO6 ": ["BDPLT7", " SCTS", " TMEM16F", "ANO6 "]},
{"ANOS1 ": ["ADMLX", " HH1", " HHA", " KAL", " KAL1", " KALIG-1", " KMS", " WFDC19", "ANOS1 "]},
{"ANTXR1 ": ["ATR", " GAPO", " TEM8", "ANTXR1 "]},
{"ANTXR2 ": ["CMG-2", " CMG2", " HFS", " ISH", " JHF", "ANTXR2 "]},
{"ANXA11 ": ["ALS23", " ANX11", " CAP-50", " CAP50", "ANXA11 "]},
{"ANXA5 ": ["ANX5", " ENX2", " HEL-S-7", " PP4", " RPRGL3", "ANXA5 "]},
{"AP1B1 ": ["ADTB1", " AP105A", " BAM22", " CLAPB2", " KIDAR", "AP1B1 "]},
{"AP1S1 ": ["AP19", " CLAPS1", " EKV3", " MEDNIK", " SIGMA1A", "AP1S1 "]},
{"AP1S2 ": ["DC22", " MRX59", " MRXS21", " MRXS5", " MRXSF", " PGS", " SIGMA1B", "AP1S2 "]},
{"AP1S3 ": ["PSORS15", "AP1S3 "]},
{"AP2M1 ": ["AP50", " CLAPM1", " MRD60", " mu2", "AP2M1 "]},
{"AP2S1 ": ["AP17", " CLAPS2", " FBH3", " FBHOk", " HHC3", "AP2S1 "]},
{"AP3B1 ": ["ADTB3", " ADTB3A", " HPS", " HPS2", " PE", "AP3B1 "]},
{"AP3B2 ": ["EIEE48", " NAPTB", "AP3B2 "]},
{"AP3D1 ": ["ADTD", " HPS10", " hBLVR", "AP3D1 "]},
{"AP4B1 ": ["BETA-4", " CPSQ5", " SPG47", "AP4B1 "]},
{"AP4E1 ": ["CPSQ4", " SPG51", " STUT1", "AP4E1 "]},
{"AP4M1 ": ["CPSQ3", " MU-4", " MU-ARP2", " SPG50", "AP4M1 "]},
{"AP4S1 ": ["AP47B", " CLA20", " CLAPS4", " CPSQ6", " SPG52", "AP4S1 "]},
{"AP5Z1 ": ["KIAA0415", " SPG48", " zeta", "AP5Z1 "]},
{"APC ": ["BTPS2", " DESMD", " DP2", " DP2.5", " DP3", " GS", " PPP1R46", "APC "]},
{"APC2 ": ["APCL", "APC2 "]},
{"APCDD1 ": ["B7323", " DRAPC1", " FP7019", " HHS", " HTS", " HYPT1", "APCDD1 "]},
{"APOA1 ": ["HPALP2", " apo(a)", "APOA1 "]},
{"APOA2 ": ["Apo-AII", " ApoA-II", " apoAII", "APOA2 "]},
{"APOA5 ": ["APOAV", " RAP3", "APOA5 "]},
{"APOB ": ["FCHL2", " FLDB", " LDLCQ4", " apoB-100", " apoB-48", "APOB "]},
{"APOC2 ": ["APO-CII", " APOC-II", "APOC2 "]},
{"APOC3 ": ["APOCIII", "APOC3 "]},
{"ACKR1 ": ["CCBP1", " CD234", " DARC", " DARC/ACKR1", " Dfy", " FY", " GPD", " GpFy", " WBCQ1", "ACKR1 "]},
{"APOL1 ": ["APO-L", " APOL", " APOL-I", " FSGS4", "APOL1 "]},
{"APOL2 ": ["APOL-II", " APOL3", "APOL2 "]},
{"APOL4 ": ["APOL-IV", " APOLIV", "APOL4 "]},
{"APP ": ["AAA", " ABETA", " ABPP", " AD1", " APPI", " CTFgamma", " CVAP", " PN-II", " PN2", " preA4", "APP "]},
{"APPL1 ": ["APPL", " DIP13alpha", " MODY14", "APPL1 "]},
{"APRT ": ["AMP", " APRTD", "APRT "]},
{"APTX ": ["AOA", " AOA1", " AXA1", " EAOH", " EOAHA", " FHA-HIT", "APTX "]},
{"AQP1 ": ["AQP-CHIP", " CHIP28", " CO", "AQP1 "]},
{"AQP2 ": ["AQP-CD", " WCH-CD", "AQP2 "]},
{"AQP3 ": ["AQP-3", " GIL", "AQP3 "]},
{"AQP5 ": ["AQP-5", " PPKB", "AQP5 "]},
{"AQP7 ": ["AQP7L", " AQPap", " GLYCQTL", "AQP7 "]},
{"AR ": ["AIS", " AR8", " DHTR", " HUMARA", " HYSP1", " KD", " NR3C4", " SBMA", " SMAX1", " TFM", "AR "]},
{"ARCN1 ": ["COPD", " SRMMD", "ARCN1 "]},
{"ARF1 ": ["PVNH8", "ARF1 "]},
{"ARFGEF2 ": ["BIG2", " PVNH2", " dJ1164I10.1", "ARFGEF2 "]},
{"ARG1 ": ["ARG1 "]},
{"ARHGAP26 ": ["GRAF", " GRAF1", " OPHN1L", " OPHN1L1", "ARHGAP26 "]},
{"ARHGAP31 ": ["AOS1", " CDGAP", "ARHGAP31 "]},
{"ARHGDIA ": ["GDIA1", " HEL-S-47e", " NPHS8", " RHOGDI", " RHOGDI-1", "ARHGDIA "]},
{"ARHGEF1 ": ["GEF1", " IMD62", " LBCL2", " LSC", " P115-RHOGEF", " SUB1.5", "ARHGEF1 "]},
{"ARHGEF10 ": ["GEF10", " SNCV", "ARHGEF10 "]},
{"ARHGEF18 ": ["P114-RhoGEF", " RP78", " SA-RhoGEF", " p114RhoGEF", "ARHGEF18 "]},
{"ARHGEF2 ": ["GEF", " GEF-H1", " GEFH1", " LFP40", " Lfc", " NEDMHM", " P40", "ARHGEF2 "]},
{"ARHGEF9 ": ["COLLYBISTIN", " EIEE8", " HPEM-2", " PEM-2", " PEM2", "ARHGEF9 "]},
{"ARID1A ": ["B120", " BAF250", " BAF250a", " BM029", " C1orf4", " CSS2", " ELD", " MRD14", " OSA1", " P270", " SMARCF1", " hELD", " hOSA1", "ARID1A "]},
{"ARID1B ": ["6A3-5", " BAF250B", " BRIGHT", " CSS1", " DAN15", " ELD/OSA1", " MRD12", " OSA2", " P250R", "ARID1B "]},
{"ARID2 ": ["BAF200", " CSS6", " p200", "ARID2 "]},
{"ARL13B ": ["ARL2L1", " JBTS8", "ARL13B "]},
{" ": [" "]},
{"ARL3 ": ["ARFL3", " JBTS35", " RP83", "ARL3 "]},
{"ARL6 ": ["BBS3", " RP55", "ARL6 "]},
{"ARL6IP1 ": ["AIP1", " ARL6IP", " ARMER", " SPG61", "ARL6IP1 "]},
{"ARMC2 ": ["SPGF38", " bA787I22.1", "ARMC2 "]},
{"ARMC4 ": ["CILD23", " gudu", "ARMC4 "]},
{"ARMC5 ": ["AIMAH2", "ARMC5 "]},
{"ARMC9 ": ["ARM", " JBTS30", " KU-MEL-1", " NS21", "ARMC9 "]},
{"ARMS2 ": ["ARMD8", "ARMS2 "]},
{"ARNT2 ": ["WEDAS", " bHLHe1", "ARNT2 "]},
{"ARPC1B ": ["ARC41", " PLTEID", " p40-ARC", " p41-ARC", "ARPC1B "]},
{"ARR3 ": ["ARRX", " MYP26", " cArr", "ARR3 "]},
{"ARSA ": ["ASA", " MLD", "ARSA "]},
{" ": [" "]},
{"ARSG ": ["USH4", "ARSG "]},
{"ARSL ": ["ARSE", " ASE", " CDPX", " CDPX1", " CDPXR", "ARSL "]},
{"ART4 ": ["ARTC4", " CD297", " DO", " DO/ART4", " DOK1", "ART4 "]},
{"ARV1 ": ["EIEE38", "ARV1 "]},
{"ARX ": ["CT121", " EIEE1", " ISSX", " MRX29", " MRX32", " MRX33", " MRX36", " MRX38", " MRX43", " MRX54", " MRX76", " MRX87", " MRXS1", " PRTS", "ARX "]},
{"ASAH1 ": ["AC", " ACDase", " ASAH", " PHP", " PHP32", " SMAPME", "ASAH1 "]},
{"ACKR1 ": ["CCBP1", " CD234", " DARC", " DARC/ACKR1", " Dfy", " FY", " GPD", " GpFy", " WBCQ1", "ACKR1 "]},
{"ASCC1 ": ["ASC1p50", " CGI-18", " SMABF2", " p50", "ASCC1 "]},
{"ASCL1 ": ["ASH1", " HASH1", " MASH1", " bHLHa46", "ASCL1 "]},
{"ASH1L ": ["ASH1", " ASH1L1", " KMT2H", " MRD52", "ASH1L "]},
{"ASIP ": ["AGSW", " AGTI", " AGTIL", " ASP", " SHEP9", "ASIP "]},
{"ASL ": ["ASAL", "ASL "]},
{"ASNS ": ["ASNSD", " TS11", "ASNS "]},
{"ASPA ": ["ACY2", " ASP", "ASPA "]},
{"ASPH ": ["AAH", " BAH", " CASQ2BP1", " FDLAB", " HAAH", " JCTN", " junctin", "ASPH "]},
{"ASPM ": ["ASP", " Calmbp1", " MCPH5", "ASPM "]},
{"ASPN ": ["OS3", " PLAP-1", " PLAP1", " SLRR1C", "ASPN "]},
{"ASPSCR1 ": ["ASPCR1", " ASPL", " ASPS", " RCC17", " TUG", " UBXD9", " UBXN9", "ASPSCR1 "]},
{"ASS1 ": ["ASS", " CTLN1", "ASS1 "]},
{"ASXL1 ": ["BOPS", " MDS", "ASXL1 "]},
{"ASXL2 ": ["ASXH2", " SHAPNS", "ASXL2 "]},
{"ASXL3 ": ["BRPS", " KIAA1713", "ASXL3 "]},
{"ATAD1 ": ["AFDC1", " FNP001", " HKPX4", " Msp1", " THORASE", "ATAD1 "]},
{"ATAD3A ": ["HAYOS", " PHRINL", "ATAD3A "]},
{"ATCAY ": ["BNIP-H", " CLAC", "ATCAY "]},
{"ATF6 ": ["ACHM7", " ATF6A", "ATF6 "]},
{"ATG16L1 ": ["APG16L", " ATG16A", " ATG16L", " IBD10", " WDR30", "ATG16L1 "]},
{"ATG5 ": ["APG5", " APG5-LIKE", " APG5L", " ASP", " SCAR25", " hAPG5", "ATG5 "]},
{"ATIC ": ["AICAR", " AICARFT", " HEL-S-70p", " IMPCHASE", " PURH", "ATIC "]},
{"ATL1 ": ["AD-FSP", " FSP1", " GBP3", " HSN1D", " SPG3", " SPG3A", " atlastin1", "ATL1 "]},
{"ATL3 ": ["HSN1F", "ATL3 "]},
{"ATM ": ["AT1", " ATA", " ATC", " ATD", " ATDC", " ATE", " TEL1", " TELO1", "ATM "]},
{"ATN1 ": ["B37", " CHEDDA", " D12S755E", " DRPLA", " HRS", " NOD", "ATN1 "]},
{"ATOH7 ": ["Math5", " NCRNA", " PHPVAR", " RNANC", " bHLHa13", "ATOH7 "]},
{"ATP11C ": ["ATPIG", " ATPIQ", " HACXL", "ATP11C "]},
{"ATP13A2 ": ["CLN12", " HSA9947", " KRPPD", " PARK9", " SPG78", "ATP13A2 "]},
{"ATP1A1 ": ["CMT2DD", " HOMGSMR2", "ATP1A1 "]},
{"ATP1A2 ": ["FHM2", " MHP2", "ATP1A2 "]},
{"ATP1A3 ": ["AHC2", " ATP1A1", " CAPOS", " DYT12", " RDP", "ATP1A3 "]},
{"ATP1B1 ": ["ATP1B", "ATP1B1 "]},
{"ATP2A1 ": ["ATP2A", " SERCA1", "ATP2A1 "]},
{"ATP2A2 ": ["ATP2B", " DAR", " DD", " SERCA2", "ATP2A2 "]},
{"ATP2B2 ": ["PMCA2", " PMCA2a", " PMCA2i", "ATP2B2 "]},
{"ATP2B3 ": ["CFAP39", " CLA2", " OPCA", " PMCA3", " PMCA3a", " SCAX1", "ATP2B3 "]},
{"ATP2C1 ": ["ATP2C1A", " BCPM", " HHD", " PMR1", " SPCA1", " hSPCA1", "ATP2C1 "]},
{"ATP5F1A ": ["ATP5A", " ATP5A1", " ATP5AL2", " ATPM", " COXPD22", " HEL-S-123m", " MC5DN4", " MOM2", " OMR", " ORM", " hATP1", "ATP5F1A "]},
{"ATP5F1D ": ["ATP5D", " MC5DN5", "ATP5F1D "]},
{"ATP5F1E ": ["ATP5E", " ATPE", " MC5DN3", "ATP5F1E "]},
{"ATP5MD ": ["DAPIT", " HCVFTP2", " MC5DN6", " USMG5", " bA792D24.4", "ATP5MD "]},
{"ATP6 ": ["ATPase6", " MTATP6", "ATP6 "]},
{"ATP6AP1 ": ["16A", " ATP6IP1", " ATP6S1", " Ac45", " CF2", " VATPS1", " XAP-3", " XAP3", "ATP6AP1 "]},
{"ATP6AP2 ": ["APT6M8-9", " ATP6IP2", " ATP6M8-9", " CDG2R", " ELDF10", " HT028", " M8-9", " MRXE", " MRXSH", " MSTP009", " PRR", " RENR", " XMRE", " XPDS", "ATP6AP2 "]},
{"ATP6V0A2 ": ["A2", " ARCL", " ARCL2A", " ATP6A2", " ATP6N1D", " J6B7", " RTF", " STV1", " TJ6", " TJ6M", " TJ6S", " VPH1", " WSS", "ATP6V0A2 "]},
{"ATP6V0A4 ": ["A4", " ATP6N1B", " ATP6N2", " RDRTA2", " RTA1C", " RTADR", " STV1", " VPH1", " VPP2", "ATP6V0A4 "]},
{"ATP6V1A ": ["ARCL2D", " ATP6A1", " ATP6V1A1", " HO68", " IECEE3", " VA68", " VPP2", " Vma1", "ATP6V1A "]},
{"ATP6V1B1 ": ["ATP6B1", " RTA1B", " VATB", " VMA2", " VPP3", "ATP6V1B1 "]},
{"ACKR1 ": ["CCBP1", " CD234", " DARC", " DARC/ACKR1", " Dfy", " FY", " GPD", " GpFy", " WBCQ1", "ACKR1 "]},
{"ATP6V1E1 ": ["ARCL2C", " ATP6E", " ATP6E2", " ATP6V1E", " P31", " Vma4", "ATP6V1E1 "]},
{"ATP7A ": ["DSMAX", " MK", " MNK", " SMAX3", "ATP7A "]},
{"ATP7B ": ["PWD", " WC1", " WD", " WND", "ATP7B "]},
{"ATP8A2 ": ["ATP", " ATPIB", " CAMRQ4", " IB", " ML-1", "ATP8A2 "]},
{"ATP8B1 ": ["ATPIC", " BRIC", " FIC1", " ICP1", " PFIC", " PFIC1", "ATP8B1 "]},
{"ATPAF2 ": ["ATP12", " ATP12p", " LP3663", " MC5DN1", "ATPAF2 "]},
{"ATR ": ["FCTCS", " FRP1", " MEC1", " SCKL", " SCKL1", "ATR "]},
{"ATRX ": ["JMS", " MRX52", " RAD54", " RAD54L", " XH2", " XNP", " ZNF-HX", "ATRX "]},
{"ATXN1 ": ["ATX1", " D6S504E", " SCA1", "ATXN1 "]},
{" ": [" "]},
{"ATXN2 ": ["ATX2", " SCA2", " TNRC13", "ATXN2 "]},
{"ATXN3 ": ["AT3", " ATX3", " JOS", " MJD", " MJD1", " SCA3", "ATXN3 "]},
{"ATXN7 ": ["ADCAII", " OPCA3", " SCA7", " SGF73", "ATXN7 "]},
{"ATXN8 ": ["ATXN8 "]},
{"ATXN8OS ": ["KLHL1AS", " NCRNA00003", " SCA8", "ATXN8OS "]},
{"AUH ": ["AUH "]},
{"AURKC ": ["AIE2", " AIK3", " ARK3", " AurC", " HEL-S-90", " SPGF5", " STK13", " aurora-C", "AURKC "]},
{"AUTS2 ": ["FBRSL2", " MRD26", "AUTS2 "]},
{"AVIL ": ["ADVIL", " DOC6", " NPHS21", " p92", "AVIL "]},
{"AVP ": ["ADH", " ARVP", " AVP-NPII", " AVRP", " VP", "AVP "]},
{"AVPR2 ": ["ADHR", " DI1", " DIR", " DIR3", " NDI", " V2R", "AVPR2 "]},
{"AXIN1 ": ["AXIN", " PPP1R49", "AXIN1 "]},
{"AXIN2 ": ["AXIL", " ODCRCS", "AXIN2 "]},
{"AXL ": ["ARK", " JTK11", " Tyro7", " UFO", "AXL "]},
{"B3GALNT1 ": ["B3GALT3", " GLCT3", " GLOB", " Gb4Cer", " P", " P1", " beta3Gal-T3", " galT3", "B3GALNT1 "]},
{"B3GALNT2 ": ["B3GalNAc-T2", " MDDGA11", "B3GALNT2 "]},
{"B3GALT6 ": ["ALGAZ", " EDSP2", " EDSSPD2", " SEMDJL1", " beta3GalT6", "B3GALT6 "]},
{"B3GAT3 ": ["GLCATI", " JDSCD", " glcUAT-I", "B3GAT3 "]},
{"B4GALNT1 ": ["GALGT", " GALNACT", " GalNAc-T", " SPG26", "B4GALNT1 "]},
{"B4GALT1 ": ["B4GAL-T1", " CDG2D", " GGTB2", " GT1", " GTB", " beta4Gal-T1", "B4GALT1 "]},
{"B4GALT7 ": ["EDSP1", " EDSSLA", " EDSSPD1", " XGALT1", " XGPT", " XGPT1", "B4GALT7 "]},
{"B4GAT1 ": ["B3GN-T1", " B3GNT1", " B3GNT6", " BETA3GNTI", " MDDGA13", " iGAT", " iGNT", "B4GAT1 "]},
{"BAAT ": ["BACAT", " BAT", "BAAT "]},
{"BACH2 ": ["BTBD25", " IMD60", "BACH2 "]},
{"BAG3 ": ["BAG-3", " BIS", " CAIR-1", " MFM6", "BAG3 "]},
{"BANF1 ": ["BAF", " BCRP1", " D14S1460", " NGPS", "BANF1 "]},
{"BAP1 ": ["HUCEP-13", " UCHL2", " hucep-6", "BAP1 "]},
{"BARD1 ": ["BARD1 "]},
{"BCAM ": ["AU", " CD239", " LU", " MSK19", "BCAM "]},
{"BCAP31 ": ["6C6-AG", " BAP31", " CDM", " DDCH", " DXS1357E", "BCAP31 "]},
{"BCKDHA ": ["BCKDE1A", " MSU", " MSUD1", " OVD1A", "BCKDHA "]},
{" ": [" "]},
{"BEAN1 ": ["BEAN", " SCA31", "BEAN1 "]},
{"BHLHA9 ": ["BHLHF42", " CCSPD", "BHLHA9 "]},
{"BLVRA ": ["BLVR", " BVR", " BVRA", "BLVRA "]},
{"BMPR1A ": ["10q23del", " ACVRLK3", " ALK3", " CD292", " SKR5", "BMPR1A "]},
{"BOLA3 ": ["MMDS2", "BOLA3 "]},
{"BRAF ": ["B-RAF1", " B-raf", " BRAF1", " NS7", " RAFB1", "BRAF "]},
{"BRAT1 ": ["BAAT1", " C7orf27", " NEDCAS", " RMFSL", "BRAT1 "]},
{"ACKR1 ": ["CCBP1", " CD234", " DARC", " DARC/ACKR1", " Dfy", " FY", " GPD", " GpFy", " WBCQ1", "ACKR1 "]},
{"BRCA2 ": ["BRCC2", " BROVCA2", " FACD", " FAD", " FAD1", " FANCD", " FANCD1", " GLM3", " PNCA2", " XRCC11", "BRCA2 "]},
{"C1GALT1C1 ": ["C1GALT2", " C38H2-L1", " COSMC", " HSPC067", " MST143", " TNPS", "C1GALT1C1 "]},
{"C1QA ": ["C1QA "]},
{"C4A ": ["C4", " C4A2", " C4A3", " C4A4", " C4A6", " C4AD", " C4S", " CO4", " CPAMD2", " RG", "C4A "]},
{"C8A ": ["C8A "]},
{"CA12 ": ["CA-XII", " CAXII", " HsT18816", " T18816", "CA12 "]},
{"CA2 ": ["CA-II", " CAC", " CAII", " Car2", " HEL-76", " HEL-S-282", "CA2 "]},
{"CA4 ": ["CAIV", " Car4", " RP17", "CA4 "]},
{"CA5A ": ["CA5", " CA5AD", " CAV", " CAVA", " GS1-21A4.1", "CA5A "]},
{"CA8 ": ["CA-RP", " CA-VIII", " CALS", " CAMRQ3", " CARP", "CA8 "]},
{"CABP2 ": ["DFNB93", "CABP2 "]},
{"CABP4 ": ["CRSD", " CSNB2B", "CABP4 "]},
{"CACNA1A ": ["APCA", " BI", " CACNL1A4", " CAV2.1", " EA2", " EIEE42", " FHM", " HPCA", " MHP", " MHP1", " SCA6", "CACNA1A "]},
{"CACNA1B ": ["BIII", " CACNL1A5", " CACNN", " Cav2.2", " DYT23", " NEDNEH", "CACNA1B "]},
{"CACNA1C ": ["CACH2", " CACN2", " CACNL1A1", " CCHL1A1", " CaV1.2", " LQT8", " TS", " TS. LQT8", "CACNA1C "]},
{"CACNA1D ": ["CACH3", " CACN4", " CACNL1A2", " CCHL1A2", " Cav1.3", " PASNA", " SANDD", "CACNA1D "]},
{"CACNA1E ": ["BII", " CACH6", " CACNL1A6", " Cav2.3", " EIEE69", " gm139", "CACNA1E "]},
{"CACNA1F ": ["AIED", " COD3", " COD4", " CORDX", " CORDX3", " CSNB2", " CSNB2A", " CSNBX2", " Cav1.4", " Cav1.4alpha1", " JM8", " JMC8", " OA2", "CACNA1F "]},
{"CACNA1G ": ["Ca(V)T.1", " Cav3.1", " NBR13", " SCA42", " SCA42ND", "CACNA1G "]},
{"CACNA1H ": ["CACNA1HB", " Cav3.2", " ECA6", " EIG6", " HALD4", "CACNA1H "]},
{"CACNA1S ": ["CACNL1A3", " CCHL1A3", " Cav1.1", " HOKPP", " HOKPP1", " MHS5", " TTPP1", " hypoPP", "CACNA1S "]},
{"CACNA2D2 ": ["CACNA2D", " CASVDD", "CACNA2D2 "]},
{"CACNA2D4 ": ["RCD4", "CACNA2D4 "]},
{"CACNB2 ": ["CAB2", " CACNLB2", " CAVB2", " MYSB", "CACNB2 "]},
{"CACNB4 ": ["CAB4", " CACNLB4", " EA5", " EIG9", " EJM", " EJM4", " EJM6", "CACNB4 "]},
{"CACNG2 ": ["MRD10", "CACNG2 "]},
{"CAD ": ["CDG1Z", " EIEE50", " GATD4", "CAD "]},
{"CALCR ": ["CRT", " CT-R", " CTR", " CTR1", "CALCR "]},
{"CALCRL ": ["CGRPR", " CRLR", " LMPHM8", "CALCRL "]},
{"CALM1 ": ["CALML2", " CAM2", " CAM3", " CAMB", " CAMC", " CAMI", " CAMIII", " CPVT4", " DD132", " LQT14", " PHKD", " caM", "CALM1 "]},
{"CALM2 ": ["CALM", " CALML2", " CAM1", " CAM3", " CAMC", " CAMII", " CAMIII", " LQT15", " PHKD", " PHKD2", " caM", "CALM2 "]},
{"CALM3 ": ["CALM", " CAM1", " CAM2", " CAMB", " CPVT6", " CaM", " CaMIII", " HEL-S-72", " LQT16", " PHKD", " PHKD3", "CALM3 "]},
{"CALR ": ["CRT", " HEL-S-99n", " RO", " SSA", " cC1qR", "CALR "]},
{"CAMK2A ": ["CAMKA", " CaMKIINalpha", " CaMKIIalpha", " MRD53", " MRT63", "CAMK2A "]},
{"CAMK2B ": ["CAM2", " CAMK2", " CAMKB", " CaMKIIbeta", " MRD54", "CAMK2B "]},
{"CAMK2G ": ["CAMK", " CAMK-II", " CAMKG", " MRD59", "CAMK2G "]},
{"CAMTA1 ": ["CANPMR", "CAMTA1 "]},
{"CANT1 ": ["DBQD", " DBQD1", " EDM7", " SCAN-1", " SCAN1", " SHAPY", "CANT1 "]},
{"CAPN1 ": ["CANP", " CANP1", " CANPL1", " SPG76", " muCANP", " muCL", "CAPN1 "]},
{"CAPN10 ": ["CANP10", " NIDDM1", "CAPN10 "]},
{"CAPN3 ": ["CANP3", " CANPL3", " LGMD2", " LGMD2A", " LGMDD4", " LGMDR1", " nCL-1", " p94", "CAPN3 "]},
{"CAPN5 ": ["ADNIV", " HTRA3", " VRNI", " nCL-3", "CAPN5 "]},
{"CARD11 ": ["BENTA", " BIMP3", " CARMA1", " IMD11", " IMD11A", " PPBL", "CARD11 "]},
{"CARD14 ": ["BIMP2", " CARMA2", " PRP", " PSORS2", " PSS1", "CARD14 "]},
{"CARD9 ": ["CANDF2", " hCARD9", "CARD9 "]},
{"CARMIL2 ": ["CARMIL2b", " IMD58", " LRRC16C", " RLTPR", "CARMIL2 "]},
{"CARS2 ": ["COXPD27", " cysRS", "CARS2 "]},
{"CARTPT ": ["CART", "CARTPT "]},
{"CASK ": ["CAGH39", " CAMGUK", " CMG", " FGS4", " LIN2", " MICPCH", " MRXSNA", " TNRC8", " hCASK", "CASK "]},
{"ACKR1 ": ["CCBP1", " CD234", " DARC", " DARC/ACKR1", " Dfy", " FY", " GPD", " GpFy", " WBCQ1", "ACKR1 "]},
{"CASP14 ": ["ARCI12", "CASP14 "]},
{"CASP8 ": ["ALPS2B", " CAP4", " Casp-8", " FLICE", " MACH", " MCH5", "CASP8 "]},
{"CASQ1 ": ["CASQ", " PDIB1", " VMCQA", "CASQ1 "]},
{"CASQ2 ": ["PDIB2", "CASQ2 "]},
{"CASR ": ["CAR", " EIG8", " FHH", " FIH", " GPRC2A", " HHC", " HHC1", " HYPOC1", " NSHPT", " PCAR1", " hCasR", "CASR "]},
{"CAST ": ["BS-17", " PLACK", "CAST "]},
{"CAT ": ["CAT "]},
{"CATSPER1 ": ["CATSPER", " SPGF7", "CATSPER1 "]},
{"CATSPER2 ": ["CATSPER2 "]},
{"CAV1 ": ["BSCL3", " CGL3", " LCCNS", " MSTP085", " PPH3", " VIP21", "CAV1 "]},
{"CAV3 ": ["LGMD1C", " LQT9", " MPDT", " RMD2", " VIP-21", " VIP21", "CAV3 "]},
{"CAVIN1 ": ["CAVIN", " CGL4", " FKSG13", " PTRF", " cavin-1", "CAVIN1 "]},
{"CC2D1A ": ["FREUD-1", " Freud-1/Aki1", " MRT3", "CC2D1A "]},
{"CC2D2A ": ["JBTS9", " MKS6", "CC2D2A "]},
{"CCDC88A ": ["APE", " GIRDIN", " GIV", " GRDN", " HkRP1", " KIAA1212", " PEHO", " PEHOL", "CCDC88A "]},
{"CD2AP ": ["CMS", "CD2AP "]},
{"CD79A ": ["IGA", " MB-1", "CD79A "]},
{"CD8A ": ["CD8", " Leu2", " p32", "CD8A "]},
{"CDAN1 ": ["CDA1", " CDAI", " CDAN1A", " DLT", " PRO1295", "CDAN1 "]},
{" ": [" "]},
{"CDCA7 ": ["ICF3", " JPO1", "CDCA7 "]},
{"CDK5RAP2 ": ["C48", " Cep215", " MCPH3", "CDK5RAP2 "]},
{"CDKN2A ": ["ARF", " CDK4I", " CDKN2", " CMM2", " INK4", " INK4A", " MLM", " MTS-1", " MTS1", " P14", " P14ARF", " P16", " P16-INK4A", " P16INK4", " P16INK4A", " P19", " P19ARF", " TP16", "CDKN2A "]},
{"CDY2A ": ["CDY", " CDY2", "CDY2A "]},
{"CEACAM16 ": ["CEAL2", " DFNA4B", " DFNB113", "CEACAM16 "]},
{"CEBPA ": ["C/EBP-alpha", " CEBP", "CEBPA "]},
{"CFAP251 ": ["CaM-IP4", " SPGF33", " WDR66", "CFAP251 "]},
{"CFAP298 ": ["C21orf48", " C21orf59", " CILD26", " FBB18", " Kur", "CFAP298 "]},
{"CFAP300 ": ["C11orf70", " CILD38", " FBB5", "CFAP300 "]},
{"CFAP410 ": ["C21orf2", " LRRC76", " RDMS", " SMDAX", " YF5/A2", "CFAP410 "]},
{"CFAP43 ": ["C10orf79", " HYDNP1", " SPGF19", " WDR96", " bA373N18.2", "CFAP43 "]},
{"CFAP44 ": ["SPGF20", " WDR52", "CFAP44 "]},
{"CFAP53 ": ["CCDC11", " HTX6", "CFAP53 "]},
{"CFAP65 ": ["CCDC108", " SPGF40", "CFAP65 "]},
{"CFAP69 ": ["C7orf63", " FAP69", " SPGF24", "CFAP69 "]},
{"CFAP70 ": ["SPGF41", " TTC18", "CFAP70 "]},
{"CHAMP1 ": ["C13orf8", " CAMP", " CHAMP", " MRD40", " ZNF828", "CHAMP1 "]},
{"CHAT ": ["CHOACTASE", " CMS1A", " CMS1A2", " CMS6", "CHAT "]},
{"CHMP1A ": ["CHMP1", " PCH8", " PCOLN3", " PRSM1", " VPS46-1", " VPS46A", "CHMP1A "]},
{"CHRNA1 ": ["ACHRA", " ACHRD", " CHRNA", " CMS1A", " CMS1B", " CMS2A", " FCCMS", " SCCMS", "CHRNA1 "]},
{"CHRNA2 ": ["CHRNA2 "]},
{"CHRNA3 ": ["BAIPRCK", " LNCR2", " NACHRA3", " PAOD2", "CHRNA3 "]},
{"CHRNA4 ": ["BFNC", " EBN", " EBN1", " NACHR", " NACHRA4", " NACRA4", "CHRNA4 "]},
{"CHRNA5 ": ["LNCR2", "CHRNA5 "]},
{"CHRNA7 ": ["CHRNA7-2", " NACHRA7", "CHRNA7 "]},
{"CIBAR1 ": ["FAM92A", " FAM92A1", " PAPA9", "CIBAR1 "]},
{"CIITA ": ["C2TA", " CIITAIV", " MHC2TA", " NLRA", "CIITA "]},
{"CKAP2L ": ["CKAP2L "]},
{"CLCNKA ": ["CLCK1", " ClC-K1", " hClC-Ka", "CLCNKA "]},
{"ACKR1 ": ["CCBP1", " CD234", " DARC", " DARC/ACKR1", " Dfy", " FY", " GPD", " GpFy", " WBCQ1", "ACKR1 "]},
{"CLEC7A ": ["BGR", " CANDF4", " CD369", " CLECSF12", " DECTIN1", " SCARE2", "CLEC7A "]},
{"CNGA1 ": ["CNCG", " CNCG1", " CNG-1", " CNG1", " RCNC1", " RCNCa", " RCNCalpha", " RP49", "CNGA1 "]},
{"CNGA3 ": ["ACHM2", " CCNC1", " CCNCa", " CCNCalpha", " CNCG3", " CNG3", "CNGA3 "]},
{"CNTNAP1 ": ["CASPR", " CHN3", " CNTNAP", " NRXN4", " P190", "CNTNAP1 "]},
{"CNTNAP2 ": ["AUTS15", " CASPR2", " CDFE", " NRXN4", " PTHSL1", "CNTNAP2 "]},
{"COA5 ": ["6330578E17Rik", " C2orf64", " CEMCOX3", " Pet191", "COA5 "]},
{"COA6 ": ["C1orf31", " CEMCOX4", "COA6 "]},
{"COA7 ": ["C1orf163", " RESA1", " SCAN3", " SELRC1", "COA7 "]},
{"COA8 ": ["APOP", " APOP1", " APOPT1", " C14orf153", "COA8 "]},
{"COASY ": ["DPCK", " NBIA6", " NBP", " PCH12", " PPAT", " UKR1", " pOV-2", "COASY "]},
{"COL10A1 ": ["COL10A1 "]},
{"COL11A1 ": ["CO11A1", " COLL6", " DFNA37", " STL2", "COL11A1 "]},
{"COL11A2 ": ["DFNA13", " DFNB53", " FBCG2", " HKE5", " OSMEDA", " OSMEDB", " PARP", " STL3", "COL11A2 "]},
{"COL12A1 ": ["BA209D8.1", " BTHLM2", " COL12A1L", " DJ234P15.1", " EDSMYP", " UCMD2", "COL12A1 "]},
{"COL13A1 ": ["CMS19", " COLXIIIA1", "COL13A1 "]},
{"COL17A1 ": ["BA16H23.2", " BP180", " BPA-2", " BPAG2", " ERED", " LAD-1", "COL17A1 "]},
{"COL18A1 ": ["GLCC", " KNO", " KNO1", " KS", "COL18A1 "]},
{"COL1A1 ": ["CAFYD", " EDSARTH1", " EDSC", " OI1", " OI2", " OI3", " OI4", "COL1A1 "]},
{"COL1A2 ": ["EDSARTH2", " EDSCV", " OI4", "COL1A2 "]},
{"COL25A1 ": ["AMY", " CFEOM5", " CLAC", " CLAC-P", " CLACP", "COL25A1 "]},
{"COL27A1 ": ["STLS", "COL27A1 "]},
{"COL2A1 ": ["ANFH", " AOM", " COL11A3", " SEDC", " STL1", "COL2A1 "]},
{"COL3A1 ": ["EDS4A", " EDSVASC", " PMGEDSV", "COL3A1 "]},
{"COL4A1 ": ["BSVD", " BSVD1", " COL4A1s", " PADMAL", " RATOR", "COL4A1 "]},
{"COL4A2 ": ["BSVD2", " ICH", " POREN2", "COL4A2 "]},
{"COL4A3 ": ["ATS2", " ATS3", "COL4A3 "]},
{"COL4A4 ": ["ATS2", " BFH", " CA44", "COL4A4 "]},
{"COL4A5 ": ["ASLN", " ATS", " ATS1", " CA54", "COL4A5 "]},
{"COL4A6 ": ["CXDELq22.3", " DELXq22.3", " DFNX6", "COL4A6 "]},
{"COL5A1 ": ["EDSC", " EDSCL1", "COL5A1 "]},
{"COL5A2 ": ["EDSC", " EDSCL2", "COL5A2 "]},
{"COL6A1 ": ["BTHLM1", " OPLL", " UCHMD1", "COL6A1 "]},
{"COL6A2 ": ["BTHLM1", " PP3610", " UCMD1", "COL6A2 "]},
{"COL6A3 ": ["BTHLM1", " DYT27", " UCMD1", "COL6A3 "]},
{"COL7A1 ": ["EBD1", " EBDCT", " EBR1", " NDNC8", "COL7A1 "]},
{"COL8A2 ": ["FECD", " FECD1", " PPCD", " PPCD2", "COL8A2 "]},
{"COL9A1 ": ["DJ149L1.1.2", " EDM6", " MED", " STL4", "COL9A1 "]},
{"COL9A2 ": ["DJ39G22.4", " EDM2", " MED", " STL5", "COL9A2 "]},
{"COL9A3 ": ["DJ885L7.4.1", " EDM3", " IDD", " MED", "COL9A3 "]},
{"COLGALT1 ": ["BSVD3", " ColGalT 1", " GLT25D1", "COLGALT1 "]},
{"COPA ": ["AILJK", " HEP-COP", " alpha-COP", "COPA "]},
{"COQ8A ": ["ADCK3", " ARCA2", " CABC1", " COQ10D4", " COQ8", " SCAR9", "COQ8A "]},
{"CORO1A ": ["CLABP", " CLIPINA", " HCORO1", " IMD8", " TACO", " p57", "CORO1A "]},
{" ": [" "]},
{"COX8A ": ["COX", " COX8", " COX8-2", " COX8L", " VIII", " VIII-L", "COX8A "]},
{"CPA6 ": ["CPAH", " ETL5", " FEB11", "CPA6 "]},
{"CPAMD8 ": ["ASGD8", " K-CAP", " VIP", "CPAMD8 "]},
{"CPLANE1 ": ["C5orf42", " Hug", " JBTS17", " OFD6", "CPLANE1 "]},
{"CPT1A ": ["CPT1", " CPT1-L", " L-CPT1", "CPT1A "]},
{" ": [" "]},
{"CRAT ": ["CAT", " CAT1", " NBIA8", "CRAT "]},
{"CRPPA ": ["ISPD", " LGMDR20", " MDDGA7", " MDDGC7", " Nip", " hISPD", "CRPPA "]},
{"CRTAP ": ["CASP", " LEPREL3", " OI7", " P3H5", "CRTAP "]},
{"CRYAA ": ["CRYA1", " CTRCT9", " HSPB4", "CRYAA "]},
{"CRYAB ": ["CMD1II", " CRYA2", " CTPP2", " CTRCT16", " HEL-S-101", " HSPB5", " MFM2", "CRYAB "]},
{"CRYBA1 ": ["CRYB1", " CTRCT10", "CRYBA1 "]},
{"CRYBA2 ": ["CTRCT42", "CRYBA2 "]},
{"CRYBA4 ": ["CTRCT23", " CYRBA4", " MCOPCT4", "CRYBA4 "]},
{"CSF2RA ": ["CD116", " CDw116", " CSF2R", " CSF2RAX", " CSF2RAY", " CSF2RX", " CSF2RY", " GM-CSF-R-alpha", " GMCSFR", " GMCSFR-alpha", " GMR", " GMR-alpha", " SMDP4", " alphaGMR", "CSF2RA "]},
{"CSNK2A1 ": ["CK2A1", " CKII", " Cka1", " Cka2", " OCNDS", "CSNK2A1 "]},
{"CSTA ": ["AREI", " PSS4", " STF1", " STFA", "CSTA "]},
{"CTLA4 ": ["ALPS5", " CD", " CD152", " CELIAC3", " CTLA-4", " GRD4", " GSE", " IDDM12", "CTLA4 "]},
{"CTNNA1 ": ["CAP102", " MDPT2", "CTNNA1 "]},
{"CTNNA2 ": ["CAP-R", " CAPR", " CDCBM9", " CT114", " CTNR", "CTNNA2 "]},
{"CTNNA3 ": ["ARVD13", " VR22", "CTNNA3 "]},
{"CTSA ": ["GLB2", " GSL", " NGBE", " PPCA", " PPGB", "CTSA "]},
{"CYB5A ": ["CYB5", " MCB5", " METAG", "CYB5A "]},
{"CYBA ": ["p22-PHOX", "CYBA "]},
{"CYP11A1 ": ["CYP11A", " CYPXIA1", " P450SCC", "CYP11A1 "]},
{"CYP17A1 ": ["CPT7", " CYP17", " P450C17", " S17AH", "CYP17A1 "]},
{"CYP19A1 ": ["ARO", " ARO1", " CPV1", " CYAR", " CYP19", " CYPXIX", " P-450AROM", "CYP19A1 "]},
{"CYP21A2 ": ["CA21H", " CAH1", " CPS1", " CYP21", " CYP21B", " P450c21B", "CYP21A2 "]},
{"CYP24A1 ": ["CP24", " CYP24", " HCAI", " HCINF1", " P450-CC24", "CYP24A1 "]},
{"CYP27A1 ": ["CP27", " CTX", " CYP27", "CYP27A1 "]},
{"CYP2A6 ": ["CPA6", " CYP2A", " CYP2A3", " CYPIIA6", " P450C2A", " P450PB", "CYP2A6 "]},
{"CYP3A5 ": ["CP35", " CYPIIIA5", " P450PCN3", " PCN3", "CYP3A5 "]},
{"DAB1 ": ["SCA37", "DAB1 "]},
{"DACT1 ": ["DAPPER", " DAPPER1", " DPR1", " FRODO", " HDPR1", " TBS2", " THYEX3", "DACT1 "]},
{"DAG1 ": ["156DAG", " A3a", " AGRNR", " DAG", " LGMDR16", " MDDGA9", " MDDGC7", " MDDGC9", "DAG1 "]},
{"DAOA ": ["LG72", " SG72", "DAOA "]},
{"DARS1 ": ["DARS", " HBSL", " aspRS", "DARS1 "]},
{"DARS2 ": ["ASPRS", " LBSL", " MT-ASPRS", " mtAspRS", "DARS2 "]},
{"DAZ1 ": ["DAZ", " SPGY", "DAZ1 "]},
{"DAZ2 ": ["pDP1678", "DAZ2 "]},
{"DAZ3 ": ["pDP1679", "DAZ3 "]},
{"DCAF17 ": ["C20orf37", " C2orf37", "DCAF17 "]},
{"DCAF8 ": ["GAN2", " H326", " WDR42A", "DCAF8 "]},
{"DEAF1 ": ["MRD24", " NUDR", " SPN", " ZMYND5", "DEAF1 "]},
{"DENND5A ": ["EIEE49", " RAB6IP1", "DENND5A "]},
{"DGAT1 ": ["ARAT", " ARGP1", " DGAT", " DIAR7", "DGAT1 "]},
{"DIABLO ": ["DFNA64", " SMAC", "DIABLO "]},
{"DIAPH1 ": ["DFNA1", " DIA1", " DRF1", " LFHL1", " SCBMS", " hDIA1", "DIAPH1 "]},
{"DIAPH2 ": ["DIA", " DIA2", " DRF2", " POF", " POF2", " POF2A", "DIAPH2 "]},
{"DIAPH3 ": ["AN", " AUNA1", " DIA2", " DRF3", " NSDAN", " diap3", " mDia2", "DIAPH3 "]},
{"DLAT ": ["DLTA", " E2", " PBC", " PDC-E2", " PDCE2", "DLAT "]},
{"DNA2 ": ["DNA2L", " hDNA2", "DNA2 "]},
{"DNAAF1 ": ["CILD13", " DAU1", " LRRC50", " ODA7", " swt", "DNAAF1 "]},
{"DNAAF2 ": ["C14orf104", " CILD10", " KTU", " PF13", "DNAAF2 "]},
{"DNAAF3 ": ["C19orf51", " CILD2", " DAB1", " PCD", " PF22", "DNAAF3 "]},
{"ACKR1 ": ["CCBP1", " CD234", " DARC", " DARC/ACKR1", " Dfy", " FY", " GPD", " GpFy", " WBCQ1", "ACKR1 "]},
{"DNAAF5 ": ["CILD18", " HEATR2", "DNAAF5 "]},
{"DNAAF6 ": ["CILD36", " CXorf41", " NYSAR97", " PIH1D3", " TWISTER", "DNAAF6 "]},
{"DNAH1 ": ["CILD37", " DNAHC1", " HDHC7", " HL-11", " HL11", " HSRF-1", " SPGF18", " XLHSRF-1", "DNAH1 "]},
{"DNAH11 ": ["CILD7", " DNAHBL", " DNAHC11", " DNHBL", " DPL11", "DNAH11 "]},
{"DNAH17 ": ["DNAHL1", " DNEL2", " SPGF39", "DNAH17 "]},
{"DNAH5 ": ["CILD3", " DNAHC5", " HL1", " KTGNR", " PCD", "DNAH5 "]},
{"DNAH9 ": ["CILD40", " DNAH17L", " DNEL1", " DYH9", " Dnahc9", " HL-20", " HL20", "DNAH9 "]},
{"DNAI1 ": ["CILD1", " DIC1", " ICS1", " PCD", "DNAI1 "]},
{"DNAI2 ": ["CILD9", " DIC2", "DNAI2 "]},
{"DNAJB11 ": ["ABBP-2", " ABBP2", " DJ9", " Dj-9", " EDJ", " ERdj3", " ERj3", " ERj3p", " PKD6", " PRO1080", " UNQ537", "DNAJB11 "]},
{"DNAJB13 ": ["CILD34", " RSPH16A", " TSARG5", " TSARG6", "DNAJB13 "]},
{"DNAJB2 ": ["CMT2T", " DSMA5", " HSJ-1", " HSJ1", " HSPF3", "DNAJB2 "]},
{"DNAJB6 ": ["DJ4", " DnaJ", " HHDJ1", " HSJ-2", " HSJ2", " LGMD1D", " LGMD1E", " LGMDD1", " MRJ", " MSJ-1", "DNAJB6 "]},
{"DNAJC12 ": ["HPANBH4", " JDP1", "DNAJC12 "]},
{"DNAJC19 ": ["PAM18", " TIM14", " TIMM14", "DNAJC19 "]},
{"DNAJC21 ": ["BMFS3", " DNAJA5", " GS3", " JJJ1", "DNAJC21 "]},
{" ": [" "]},
{"DNAJC5 ": ["CLN4", " CLN4B", " CSP", " DNAJC5A", " NCL", " mir-941-2", " mir-941-3", " mir-941-4", " mir-941-5", "DNAJC5 "]},
{"DNAJC6 ": ["DJC6", " PARK19", "DNAJC6 "]},
{"DNAL1 ": ["C14orf168", " CILD16", " LC1", "DNAL1 "]}
]